tsCaptum/_forwarder.py
tsCaptum/_ridge_classifier.py
tsCaptum/_tsCaptum_loader.py
tsCaptum/_utils.py
tsCaptum/explainers.py
tsCaptum/visualization.py
tsCaptum-0.0.5.dist-info/LICENSE
tsCaptum-0.0.5.dist-info/METADATA
tsCaptum-0.0.5.dist-info/WHEEL
tsCaptum-0.0.5.dist-info/top_level.txt
tsCaptum-0.0.5.dist-info/RECORD
