Metadata-Version: 2.1
Name: tsCaptum
Version: 0.0.5
Summary: A Captum wrapper for Time Series XAI
Author-email: Davide Serramazza <davide.serramazza@ucdconnect.ie>
Project-URL: Homepage, https://github.com/mlgig/tscaptum/
Requires-Python: <3.12,>=3.8
License-File: LICENSE
Requires-Dist: scikit-learn
Requires-Dist: aeon >=0.10.0
Requires-Dist: openpyxl
Requires-Dist: tqdm
Requires-Dist: torch >=2.0.0
Requires-Dist: captum ==0.7.0
